{
    "product-insteadofprice": "9,49",
    "product-badge-image": "",
    "url": "https://www.spar.si/online/belo-vino-chardonnay-carga-075l/p/611272",
    "title": "BELO VINO CHARDONNAY, ČARGA, 0,75L",
    "product-promotionBadges": "",
    "isOnPromotion": "false",
    "product-price": "9,49",
    "product-info": {
        "trade-group": {
            "vsebnost-alkohola": "13,00 vol. %"
        },
        "product-net-cont": {
            "neto-količina": "0,75l"
        },
        "\n\t\t\t\ttehnično-ime-izdelka": "CHARDONNAY 2020, SUHO KAKOVOSTNO VINO,  VINOGRADNIŠTVO IN VINARSTVO ČARGA 1767",
        "contact-information": {
            "kontakt:": "VINOGRADNIŠTVO IN VINARSTVO ČARGA 1767, Martin Erzetič"
        },
        "ingredient-information": {
            "alergeni": "ŽVEPLOV DIOKSID IN SULFITI."
        },
        "\n\t\t\t\tprehrambni-tip-artikla": "ni relevantno"
    },
    "product-priceperunit": "12,65 €/l",
    "teaser-text": "VINO CHAR.ČARGA 0,75L",
    "product-badge-hostname": "https://www.spar.si",
    "product-stock-status": "",
    "product-amount": "",
    "description": "VINO CHAR.ČARGA 0,75L",
    "teaser-image": "https://cdn1.interspar.at/cachableservlets/articleImage.dam/si/611272/dt_main.jpg",
    "product-brand": ""
}