{
    "product-insteadofprice": "5,25",
    "product-badge-image": "",
    "url": "https://www.spar.si/online/briketi-za-macke-piscanec-in-zelenjava-hairball-friskies-purina-15kg/p/527078",
    "title": "BRIKETI ZA MAČKE PIŠČANEC IN ZELENJAVA HAIRBALL, FRISKIES, PURINA, 1,5KG",
    "product-promotionBadges": "",
    "isOnPromotion": "false",
    "product-price": "5,25",
    "product-info": {
        "product-net-cont": {
            "neto-količina": "1,5kg"
        },
        "contact-information": {
            "kontakt:": "ARC-Kranj, d.o.o., Hrastje 52k, 4000 Kranj"
        },
        "ingredient-information": {
            "temperatura-za-hranjenje": "sobna temperatura"
        }
    },
    "product-priceperunit": "3,50 €/kg",
    "teaser-text": "BRIKETI HAIRBALL 1,5KG",
    "product-badge-hostname": "https://www.spar.si",
    "product-stock-status": "",
    "product-amount": "",
    "description": "BRIKETI HAIRBALL 1,5KG",
    "teaser-image": "https://cdn1.interspar.at/cachableservlets/articleImage.dam/si/527078/dt_main.jpg",
    "product-brand": ""
}