{
    "product-promotionBadges": "Izdelek v promociji",
    "product-insteadofprice": "21,79",
    "product-stock-status": "",
    "product-info": {
        "product-net-cont": {
            "neto-količina": "1kos"
        },
        "contact-information": {
            "kontakt:": "Orbico d.o.o., Verovškova ulica 72, 1000 Ljubljana, Slovenija"
        }
    },
    "product-priceperunit": "16,34 €/kos",
    "product-brand": "",
    "url": "https://www.spar.si/online/britvica-5-rezil-power-flexball-proglide-gillette-11/p/492286",
    "product-price": "16,34",
    "title": "BRITVICA 5 REZIL POWER FLEXBALL PROGLIDE, GILLETTE, 1/1",
    "description": "BRIV.GILLETTE PROG: 1/1",
    "isOnPromotion": "true",
    "product-badge-hostname": "https://www.spar.si",
    "product-badge-image": "/online/medias/sys_master/root/h42/h77/9039969648670/akcija-1.png",
    "product-amount": "",
    "teaser-image": "https://cdn1.interspar.at/cachableservlets/articleImage.dam/si/492286/dt_main.jpg",
    "teaser-text": "BRIV.GILLETTE PROG: 1/1"
}