{
    "product-promotionBadges": "Izdelek v promociji",
    "product-insteadofprice": "8,72",
    "product-stock-status": "",
    "product-info": {
        "product-net-cont": {
            "neto-količina": "1kos"
        },
        "contact-information": {
            "kontakt:": "Orbico d.o.o., Verovškova ulica 72, 1000 Ljubljana, Slovenija"
        }
    },
    "product-priceperunit": "6,54 €/kos",
    "product-brand": "",
    "url": "https://www.spar.si/online/britvice-mach3-start-gillette-11-2-nadomestna-nastavka/p/544590",
    "product-price": "6,54",
    "title": "BRITVICE MACH3 START, GILLETTE, 1/1 + 2 NADOMESTNA NASTAVKA",
    "description": "BRIVNIK GILLETTE MACH3",
    "isOnPromotion": "true",
    "product-badge-hostname": "https://www.spar.si",
    "product-badge-image": "/online/medias/sys_master/root/h42/h77/9039969648670/akcija-1.png",
    "product-amount": "",
    "teaser-image": "https://cdn1.interspar.at/cachableservlets/articleImage.dam/si/544590/dt_main.jpg",
    "teaser-text": "BRIVNIK GILLETTE MACH3"
}