{
    "product-info": {
        "product-net-cont": {
            "neto-količina": "1kos"
        },
        "opis": "Set vsebuje:- NIVEA MEN Active Energy antiperspirant, 150ml- NIVEA MEN Active Energy gel za tuširanje, 250ml"
    },
    "product-brand": "",
    "url": "https://www.spar.si/online/darilni-set-active-energy-nivea-men-21/p/610063",
    "product-price": "4,33",
    "teaser-image": "https://cdn1.interspar.at/cachableservlets/articleImage.dam/si/610063/dt_main.jpg",
    "product-badge-hostname": "https://www.spar.si",
    "product-badge-image": "/online/medias/sys_master/root/h42/h77/9039969648670/akcija-1.png",
    "product-insteadofprice": "6,19",
    "product-amount": "",
    "isOnPromotion": "true",
    "product-promotionBadges": "Izdelek v promociji",
    "teaser-text": "DARILNI SET NIVEA MEN",
    "product-stock-status": "",
    "title": "DARILNI SET ACTIVE ENERGY, NIVEA MEN, 2/1",
    "product-priceperunit": "4,33 €/kos",
    "description": "DARILNI SET NIVEA MEN"
}