{
    "product-insteadofprice": "28,99",
    "product-badge-image": "/online/medias/sys_master/images/images/hc5/h14/9039970304030/bio-1.png",
    "url": "https://www.spar.si/online/eko-zganje-baby-blue-035l/p/612905",
    "title": "EKO ŽGANJE BABY BLUE, 0,35L",
    "product-promotionBadges": "",
    "isOnPromotion": "false",
    "product-price": "28,99",
    "product-info": {
        "trade-group": {
            "vsebnost-alkohola": "40,00 vol. %"
        },
        "product-net-cont": {
            "neto-količina": "0,35l"
        },
        "\n\t\t\t\ttehnično-ime-izdelka": "ŽGANJE BABY BLUE EKO 0,35L BABY BLUE, 40% ALK.",
        "contact-information": {
            "kontakt:": "PANORGANIX D.O.O."
        },
        "\n\t\t\t\tprehrambni-tip-artikla": "ni relevantno",
        "product-badges": {
            "certifikati": "BIO Certifikat"
        }
    },
    "product-priceperunit": "82,83 €/l",
    "teaser-text": "ŽGANJE BABY BLUE 0,35L",
    "product-badge-hostname": "https://www.spar.si",
    "product-stock-status": "",
    "product-amount": "",
    "description": "ŽGANJE BABY BLUE 0,35L",
    "teaser-image": "https://cdn1.interspar.at/cachableservlets/articleImage.dam/si/612905/dt_main.jpg",
    "product-brand": ""
}