{
    "product-priceperunit": "17,60 €/l",
    "title": "GEL ZA BRITJE ALOE VERA, GILLETTE, 200ML",
    "product-info": {
        "product-net-cont": {
            "neto-količina": "0,2l"
        },
        "contact-information": {
            "kontakt:": "Orbico d.o.o., Verovškova ulica 72, 1000 Ljubljana, Slovenija"
        },
        "ingredient-information": {}
    },
    "product-stock-status": "",
    "product-price": "3,52",
    "product-badge-hostname": "https://www.spar.si",
    "url": "https://www.spar.si/online/gel-za-britje-aloe-vera-gillette-200ml/p/112686",
    "product-amount": "",
    "product-promotionBadges": "Izdelek v promociji",
    "product-brand": "",
    "description": "GEL GILLETTE SATIN 200ML",
    "teaser-image": "https://cdn1.interspar.at/cachableservlets/articleImage.dam/si/112686/dt_main.jpg",
    "isOnPromotion": "true",
    "product-insteadofprice": "4,69",
    "product-badge-image": "/online/medias/sys_master/root/h42/h77/9039969648670/akcija-1.png",
    "teaser-text": "GEL GILLETTE SATIN 200ML"
}