{
    "product-insteadofprice": "3,99",
    "product-priceperunit": "13,13 €/kg",
    "product-badge-hostname": "https://www.spar.si",
    "product-badge-image": "",
    "title": "INSTANT KAVA 3V1 ORIGINAL, JACOBS, 20/1, 304G",
    "product-stock-status": "",
    "product-info": {
        "ingredient-information": {
            "alergeni": "MLEKO."
        },
        "product-net-cont": {
            "neto-količina": "304g"
        },
        "contact-information": {
            "kontakt:": "ORBICO D.O.O."
        }
    },
    "description": "KAVA INS.JACOBS 3V1 304G",
    "product-promotionBadges": "",
    "product-brand": "",
    "product-price": "3,99",
    "teaser-text": "KAVA INS.JACOBS 3V1 304G",
    "isOnPromotion": "false",
    "url": "https://www.spar.si/online/instant-kava-3v1-original-jacobs-201-304g/p/479840",
    "product-amount": "",
    "teaser-image": "https://cdn1.interspar.at/cachableservlets/articleImage.dam/si/479840/dt_main.jpg"
}