{
    "product-insteadofprice": "39,99",
    "product-badge-image": "",
    "url": "https://www.spar.si/online/irski-whiskey-single-grain-teeling-07l/p/598680",
    "title": "IRSKI WHISKEY SINGLE GRAIN, TEELING, 0,7L",
    "product-promotionBadges": "",
    "isOnPromotion": "false",
    "product-price": "39,99",
    "product-info": {
        "trade-group": {
            "vsebnost-alkohola": "46,00 vol. %"
        },
        "product-net-cont": {
            "neto-količina": "0,7l"
        },
        "\n\t\t\t\ttehnično-ime-izdelka": "VISKI TEELING SINGLE GRAIN, 0,7L, 46% ALK., IRSKA",
        "contact-information": {
            "kontakt:": "Ekskluzivna darila d.o.o."
        },
        "ingredient-information": {
            "temperatura-za-hranjenje": "sobna temperatura"
        },
        "\n\t\t\t\tprehrambni-tip-artikla": "ni relevantno"
    },
    "product-priceperunit": "57,13 €/l",
    "teaser-text": "WH.TEELING S.GRAIN 0,7L",
    "product-badge-hostname": "https://www.spar.si",
    "product-stock-status": "",
    "product-amount": "",
    "description": "WH.TEELING S.GRAIN 0,7L",
    "teaser-image": "https://cdn1.interspar.at/cachableservlets/articleImage.dam/si/598680/dt_main.jpg",
    "product-brand": ""
}