{
    "title": "JABOLČNI KIS, TALIS, 1L",
    "product-badge-image": "",
    "teaser-image": "https://cdn1.interspar.at/cachableservlets/articleImage.dam/si/349123/dt_main.jpg",
    "product-badge-hostname": "https://www.spar.si",
    "product-insteadofprice": "1,66",
    "isOnPromotion": "false",
    "product-info": {
        "product-net-cont": {
            "neto-količina": "1l"
        },
        "\n\t\t\t\ttehnično-ime-izdelka": "Jabolčni kis s 5 % kislosti",
        "contact-information": {
            "kontakt:": "ETA KAMNIK d.o.o., Kajuhova pot 4, 1241 Kamnik"
        },
        "opis": "Jabolčni kis je izdelan po naravnem biotehnološkem postopku.",
        "\n\t\t\t\tprehrambni-tip-artikla": "pakiran izdelek v normalni atmosferi",
        "ingredient-information": {
            "alergeni": "ŽVEPLOV DIOKSID IN SULFITI."
        }
    },
    "product-brand": "",
    "product-amount": "",
    "product-priceperunit": "1,66 €/l",
    "product-stock-status": "",
    "description": "KIS JABOLČNI 1L TALIS",
    "product-price": "1,66",
    "product-promotionBadges": "",
    "teaser-text": "KIS JABOLČNI 1L TALIS",
    "url": "https://www.spar.si/online/jabolcni-kis-talis-1l/p/349123"
}