{
    "title": "JABOLKA GALA, 1KG",
    "product-badge-image": "/online/medias/sys_master/images/images/h3b/h64/9829227331614/tehtnica-ikona-123x80.jpg",
    "teaser-image": "https://cdn1.interspar.at/cachableservlets/articleImage.dam/si/296981/dt_main.jpg",
    "product-badge-hostname": "https://www.spar.si",
    "product-insteadofprice": "1,89",
    "isOnPromotion": "false",
    "product-info": {
        "product-net-cont": {
            "neto-količina": "1kg"
        },
        "contact-information": {
            "kontakt:": "Različni dobavitelji"
        },
        "opis": "Izvor: novozelandska sorta uvedena v pridelavo 1965Plod: je srednje droben do srednje debel, barva je rumenkasta, ki jo prekriva intenzivno rdeča barvaOkus: s...",
        "trade-group": {
            "razred": "1"
        }
    },
    "product-brand": "",
    "product-amount": "",
    "product-priceperunit": "1,89 €/kg",
    "product-stock-status": "",
    "description": "JABOLKA GALA",
    "product-price": "1,89",
    "product-promotionBadges": "Tehtan izdelek",
    "teaser-text": "JABOLKA GALA",
    "url": "https://www.spar.si/online/jabolka-gala-1kg/p/296981"
}