{
    "product-info": {
        "product-net-cont": {
            "neto-količina": "65g"
        },
        "contact-information": {
            "kontakt:": "Lomas d.o.o, Kardeljeva ploščad 11a, 1000 Ljubljana"
        },
        "ingredient-information": {
            "sestavine": "Aqua, Stearic acid, Glycerin, Potassium hydroxide, Coconut acid, Cocos nucifera oil, Sodium hydroxide, Parfum, Sodium silicate, Cocos nucifera extract, Potassium chloride, Hydroxyisohexyl, 3-cyclohexene carboxaldehyde, Limonene, CI 42051, CI 45350, CI 47005, CI 15985"
        }
    },
    "product-brand": "",
    "url": "https://www.spar.si/online/krema-za-britje-classic-palmolive-65g/p/176036",
    "product-price": "1,59",
    "teaser-image": "https://cdn1.interspar.at/cachableservlets/articleImage.dam/si/176036/dt_main.jpg",
    "product-badge-hostname": "https://www.spar.si",
    "product-badge-image": "",
    "product-insteadofprice": "1,59",
    "product-amount": "",
    "isOnPromotion": "false",
    "product-promotionBadges": "",
    "teaser-text": "KREMA ZA BR. PALMOLIVE",
    "product-stock-status": "",
    "title": "KREMA ZA BRITJE CLASSIC PALMOLIVE, 65G",
    "product-priceperunit": "24,46 €/kg",
    "description": "KREMA ZA BR. PALMOLIVE"
}