{
    "product-promotionBadges": "Izdelek v promociji",
    "product-insteadofprice": "2,59",
    "product-stock-status": "",
    "product-info": {
        "product-net-cont": {
            "neto-količina": "0,25l"
        },
        "ingredient-information": {},
        "opis": "NIVEA kremni gel za tuširanje Creme Care kožo naredi bolj svežo, gladko in navlaženo ter jo ovije v mehko peno in edinstven vonj. Negovalna formula s provitaminom B5, hranilnimi olji in edinstvenim vonjem kreme NIVEA poskrbi za občutek sveže, gladke in navlažene kože.Izdelek ohranja pH ravnovesje kože. Dermatološko je dokazano, da koža izdelek dobro prenaša.",
        "instruction-for-use": {},
        "contact-information": {}
    },
    "product-priceperunit": "6,72 €/l",
    "product-brand": "",
    "url": "https://www.spar.si/online/kremni-gel-za-prhanje-creme-care-nivea-250-ml/p/464376",
    "product-price": "1,68",
    "title": "KREMNI GEL ZA PRHANJE, CREME CARE, NIVEA, 250 ML",
    "description": "GEL TUŠ NIVEA 250ML",
    "isOnPromotion": "true",
    "product-badge-hostname": "https://www.spar.si",
    "product-badge-image": "/online/medias/sys_master/root/h42/h77/9039969648670/akcija-1.png",
    "product-amount": "",
    "teaser-image": "https://cdn1.interspar.at/cachableservlets/articleImage.dam/si/464376/dt_main.jpg",
    "teaser-text": "GEL TUŠ NIVEA 250ML"
}