{
    "product-insteadofprice": "3,49",
    "product-badge-image": "",
    "url": "https://www.spar.si/online/mandljeva-krema-za-otroke-becutan-100ml/p/558542",
    "title": "MANDLJEVA KREMA ZA OTROKE, BECUTAN, 100ML",
    "product-promotionBadges": "",
    "isOnPromotion": "false",
    "product-price": "3,49",
    "product-info": {
        "product-net-cont": {
            "neto-količina": "0,1kos"
        },
        "contact-information": {
            "kontakt:": "ORBICO D.O.O., VEROVŠKOVA 72, 1000 LJUBLJANA"
        },
        "ingredient-information": {
            "sestavine": "Lanolin, Aqua, Petrolatum,Talc, Prunus Amigdalus Dulcis Oil, Zinc Oxide, Paraffinum Liquidum, Cera Alba, Cetyl Alcohol, Phenoxyethanol, Parfum, 2- Bromo - 2 Nitropropane - 1, 3- Diol."
        }
    },
    "product-priceperunit": "34,90 €/Pieces",
    "teaser-text": "KREMA BECUTAN 100ML",
    "product-badge-hostname": "https://www.spar.si",
    "product-stock-status": "",
    "product-amount": "",
    "description": "KREMA BECUTAN 100ML",
    "teaser-image": "https://cdn1.interspar.at/cachableservlets/articleImage.dam/si/558542/dt_main.jpg",
    "product-brand": ""
}