{
    "product-insteadofprice": "2,99",
    "product-badge-image": "/online/medias/sys_master/images/images/h3b/h64/9829227331614/tehtnica-ikona-123x80.jpg",
    "url": "https://www.spar.si/online/mango-1kg/p/51482",
    "title": "MANGO, 1KG",
    "product-promotionBadges": "",
    "isOnPromotion": "false",
    "product-price": "2,99",
    "product-info": {
        "trade-group": {
            "razred": "1"
        },
        "product-net-cont": {
            "neto-količina": "1kg"
        }
    },
    "product-priceperunit": "2,99 €/kg",
    "teaser-text": "MANGO",
    "product-badge-hostname": "https://www.spar.si",
    "product-stock-status": "",
    "product-amount": "",
    "description": "MANGO",
    "teaser-image": "https://cdn1.interspar.at/cachableservlets/articleImage.dam/si/51482/dt_main.jpg",
    "product-brand": ""
}