{
    "product-insteadofprice": "3,08",
    "product-badge-image": "",
    "url": "https://www.spar.si/online/mehcalec-summer-lenor-136l-xxl/p/539551",
    "title": "MEHČALEC SUMMER, LENOR, 1,36L, XXL",
    "product-promotionBadges": "",
    "isOnPromotion": "false",
    "product-price": "3,08",
    "product-info": {
        "product-net-cont": {
            "neto-količina": "1,36l"
        },
        "contact-information": {
            "kontakt:": "Orbico d.o.o., Verovškova 72, 1000 Ljubljana"
        },
        "ingredient-information": {
            "sestavine": "AquaDistearoylethyl/Dipalmitoylethyl Dimonium ChloridePARFUMIsopropyl AlcoholCocos Nucifera OilHexyl CinnamalLinaloolPolyquaternium-37Formic AcidGeraniolEthylhexyl StearateDipropylene GlycolAlpha-Isomethyl IononeHydrochloric AcidMonosodium EtidronatePhenyl MethiconeColorantC12-14 Sec-ParethBenzisothiazolinonePropionic alkyl polymerC10-12 Alkane/CycloalkaneSorbitan TrioleateSodium HydroxideSilicaCitric Acid"
        }
    },
    "product-priceperunit": "2,26 €/l",
    "teaser-text": "MEHČALEC LENOR SUMMER",
    "product-badge-hostname": "https://www.spar.si",
    "product-stock-status": "",
    "product-amount": "",
    "description": "MEHČALEC LENOR SUMMER",
    "teaser-image": "https://cdn1.interspar.at/cachableservlets/articleImage.dam/si/539551/dt_main.jpg",
    "product-brand": ""
}