{
    "product-info": {
        "product-net-cont": {
            "neto-količina": "1,42l"
        },
        "contact-information": {
            "kontakt:": "Orbico d.o.o., Verovškova 72, SI-1000 Ljubljana"
        },
        "opis": "S kolekcijo Lenor Parfumelle lahko svoja domača opravila pretvorite v izkušnjo za čutila. Njegova prefinjena več-čutna dišava je bila navdihnjena z najnovejšimi..."
    },
    "product-brand": "",
    "url": "https://www.spar.si/online/mehcalec-sunny-florets-parfumelle-happy-lenor-48pranj-142l/p/593157",
    "product-price": "5,28",
    "teaser-image": "https://cdn1.interspar.at/cachableservlets/articleImage.dam/si/593157/dt_main.jpg",
    "product-badge-hostname": "https://www.spar.si",
    "product-badge-image": "/online/medias/sys_master/root/h42/h77/9039969648670/akcija-1.png",
    "product-insteadofprice": "5,28",
    "product-amount": "",
    "isOnPromotion": "true",
    "product-promotionBadges": "Izdelek v promociji",
    "teaser-text": "MEHČALEC LENOR 1,420L",
    "product-stock-status": "",
    "title": "MEHČALEC SUNNY FLORETS PARFUMELLE HAPPY, LENOR, 48PRANJ, 1,42L",
    "product-priceperunit": "3,72 €/l",
    "description": "MEHČALEC LENOR 1,420L"
}