{
    "product-insteadofprice": "0,69",
    "product-badge-image": "",
    "url": "https://www.spar.si/online/mokra-hrana-za-macke-piscanec-craft-sheba-85g/p/570222",
    "title": "MOKRA HRANA ZA MAČKE PIŠČANEC CRAFT, SHEBA, 85G",
    "product-promotionBadges": "",
    "isOnPromotion": "false",
    "product-price": "0,69",
    "product-info": {
        "product-net-cont": {
            "neto-količina": "85g"
        },
        "contact-information": {
            "kontakt:": "Mars Overseas Holdings d.o.o., Letališka 29/a, 1000 Ljubljana"
        },
        "ingredient-information": {
            "temperatura-za-hranjenje": "sobna temperatura"
        },
        "\n\t\t\t\tprehrambni-tip-artikla": "ni relevantno",
        "\n\t\t\t\ttehnično-ime-izdelka": "MOKRA HRANA ZA MAČKE PIŠČANEC CRAFT, SHEBA, 85G"
    },
    "product-priceperunit": "8,12 €/kg",
    "teaser-text": "SHEBA CRAFT PIŠČANEC 85G",
    "product-badge-hostname": "https://www.spar.si",
    "product-stock-status": "",
    "product-amount": "",
    "description": "SHEBA CRAFT PIŠČANEC 85G",
    "teaser-image": "https://cdn1.interspar.at/cachableservlets/articleImage.dam/si/570222/dt_main.jpg",
    "product-brand": ""
}