{
    "title": "MOKRA HRANA ZA PSE PIŠČANEC IN GOVEDINA Z ZELENJAVO ADULT, PEDIGREE, 4X100G",
    "product-badge-image": "",
    "teaser-image": "https://cdn1.interspar.at/cachableservlets/articleImage.dam/si/308292/dt_main.jpg",
    "product-badge-hostname": "https://www.spar.si",
    "product-insteadofprice": "1,65",
    "isOnPromotion": "false",
    "product-info": {
        "product-net-cont": {
            "neto-količina": "400g"
        },
        "\n\t\t\t\ttehnično-ime-izdelka": "MOKRA HRANA ZA PSE, PIŠČANEC IN GOVEDINA Z ZELENJAVO, ADULT, PEDIGREE, 4 X 100 G",
        "\n\t\t\t\tprehrambni-tip-artikla": "ni relevantno",
        "contact-information": {},
        "ingredient-information": {
            "temperatura-za-hranjenje": "sobna temperatura"
        }
    },
    "product-brand": "",
    "product-amount": "",
    "product-priceperunit": "4,13 €/kg",
    "product-stock-status": "",
    "description": "PEDIGREE VREČKE 400G",
    "product-price": "1,65",
    "product-promotionBadges": "",
    "teaser-text": "PEDIGREE VREČKE 400G",
    "url": "https://www.spar.si/online/mokra-hrana-za-pse-piscanec-in-govedina-z-zelenjavo-adult-pedigree-4x100g/p/308292"
}