{
    "product-insteadofprice": "2,29",
    "product-priceperunit": "7,63 €/l",
    "product-badge-hostname": "https://www.spar.si",
    "product-badge-image": "",
    "title": "OLJNO TEKOČE MILO ARGAN, AFRODITA, 300ML",
    "product-stock-status": "",
    "product-info": {
        "opis": "Oljno tekoče milo za roke s hranljivim arganovim oljem kožo očisti, ne da bi jo pri tem izsušilo, jo hkrati izdatno neguje ter spodbuja njeno obnavljanje. Nepogrešljivo za suho, razpokano kožo.- 100 % organic argan oil- antibacterial- anti-dryness- skin-friendly pH- paraben, paraffin & silicone FREE",
        "ingredient-information": {
            "sestavine": "Aqua, Sodium Laureth Sulfate, PEG-7 Glyceryl Cocoate, Sodium Chloride, Cocamidopropyl Betaine, Argania Spinosa Kernel Oil, Niacinamide, Parfum, Citric Acid, PEG-40 Hydrogenated Castor Oil, Octocrylene, Homosalate, Butyl Methoxydibenzoylmethane, Tocopherol, Helianthus Annuus Seed Oil, Methylisothiazolinone,Methylchloroisothiazolinone, Limonene, CI 47005, CI 14720, CI 42051"
        },
        "product-net-cont": {
            "neto-količina": "0,3l"
        },
        "contact-information": {
            "kontakt:": "Kozmetika Afrodita d.o.o., Kidričeva 54, 3250 Rogaška Slatina, Slovenija"
        }
    },
    "description": "TEK.MILO AFRODITA 300ML",
    "product-promotionBadges": "",
    "product-brand": "",
    "product-price": "2,29",
    "teaser-text": "TEK.MILO AFRODITA 300ML",
    "isOnPromotion": "false",
    "url": "https://www.spar.si/online/oljno-tekoce-milo-argan-afrodita-300ml/p/503295",
    "product-amount": "",
    "teaser-image": "https://cdn1.interspar.at/cachableservlets/articleImage.dam/si/503295/dt_main.jpg"
}