{
    "title": "OLJNI ODSTRANJEVALEC LAKA ZA NOHTE, BREZ ACETONA, AROMA, AFRODITA, 125 ML",
    "product-badge-image": "",
    "teaser-image": "https://cdn1.interspar.at/cachableservlets/articleImage.dam/si/335159/dt_main.jpg",
    "product-badge-hostname": "https://www.spar.si",
    "product-insteadofprice": "3,79",
    "isOnPromotion": "false",
    "product-info": {
        "product-net-cont": {
            "neto-količina": "0,13l"
        },
        "contact-information": {
            "kontakt:": "Kozmetika Afrodita d.o.o., Kidričeva 54, 3250 Rogaška Slatina, Slovenija"
        },
        "opis": "Temeljito odstranjuje lak tako z naravnih kot umetnih nohtov, jih skupaj z obnohtno kožico neguje in ohranja prožne ter čvrste. Preprečuje obarvanost nohtov in ohranja njihovo naravno barvo.- brez acetonaOLJE GROZDNIH PEČK:Preprečuje staranje zaradi škodljivih vplivov prostih radikalov, kožo pomirja in neguje.",
        "ingredient-information": {}
    },
    "product-brand": "",
    "product-amount": "",
    "product-priceperunit": "30,32 €/l",
    "product-stock-status": "",
    "description": "ODSTR.LAKA ZA NOHTE",
    "product-price": "3,79",
    "product-promotionBadges": "",
    "teaser-text": "ODSTR.LAKA ZA NOHTE",
    "url": "https://www.spar.si/online/oljni-odstranjevalec-laka-za-nohte-brez-acetona-aroma-afrodita-125-ml/p/335159"
}