{
    "product-promotionBadges": "Izdelek v promociji",
    "product-insteadofprice": "2,49",
    "product-stock-status": "",
    "product-info": {
        "security-warning": {
            "varnostna-opozorila": "Živilo ni primerno za otroke."
        },
        "opis": "Peneče vino, polsuho. Poreklo: Francija. Barva: nežno rumena  Vonj: saden. Okus: saden in osvežilen. Spajanje s hrano: lahko aperitiv, odlično pa se poda k desertom. Temperatura serviranja: 4-6 °C.",
        "\n\t\t\t\tprehrambni-tip-artikla": "pakiran izdelek v kontrolirani atmosferi",
        "instruction-for-use": {
            "navodila-za-uporabo": "Ni posebnih navodil."
        },
        "contact-information": {
            "kontakt:": "TOBAČNA GROSIST, D.O.O., Cesta 24. junija 90, 1231 Ljubljana Črnuče"
        },
        "product-net-cont": {
            "neto-količina": "0,2l"
        },
        "\n\t\t\t\ttehnično-ime-izdelka": "VINO PENEČE JP CHENET ICE 0,2L",
        "ingredient-information": {
            "alergeni": "ŽVEPLOV DIOKSID IN SULFITI."
        },
        "trade-group": {
            "vsebnost-alkohola": "11,00 vol. %"
        }
    },
    "product-priceperunit": "9,35 €/l",
    "product-brand": "",
    "url": "https://www.spar.si/online/penece-vino-ice-edition-jp-chenet-02l/p/504241",
    "product-price": "1,87",
    "title": "PENEČE VINO ICE EDITION, J.P. CHENET, 0,2L",
    "description": "PEN.V. JP ICE 0,2L",
    "isOnPromotion": "true",
    "product-badge-hostname": "https://www.spar.si",
    "product-badge-image": "/online/medias/sys_master/root/h42/h77/9039969648670/akcija-1.png",
    "product-amount": "",
    "teaser-image": "https://cdn1.interspar.at/cachableservlets/articleImage.dam/si/504241/dt_main.jpg",
    "teaser-text": "PEN.V. JP ICE 0,2L"
}