{
    "product-promotionBadges": "Izdelek v promociji",
    "product-insteadofprice": "6,69",
    "product-stock-status": "",
    "product-info": {
        "product-net-cont": {
            "neto-količina": "11kos"
        },
        "contact-information": {
            "kontakt:": "Orbico d.o.o., Verovškova 72, 1000 Ljubljana"
        }
    },
    "product-priceperunit": "0,46 €/kos",
    "product-brand": "",
    "url": "https://www.spar.si/online/plavalne-plenice-st4-5-9-15kg-splashers-pampers-111/p/548965",
    "product-price": "5,02",
    "title": "PLAVALNE PLENICE ŠT.4-5 9-15KG, SPLASHERS, PAMPERS, 11/1",
    "description": "PLEN.PLAVALNE PAMPERS",
    "isOnPromotion": "true",
    "product-badge-hostname": "https://www.spar.si",
    "product-badge-image": "/online/medias/sys_master/root/h42/h77/9039969648670/akcija-1.png",
    "product-amount": "",
    "teaser-image": "https://cdn1.interspar.at/cachableservlets/articleImage.dam/si/548965/dt_main.jpg",
    "teaser-text": "PLEN.PLAVALNE PAMPERS"
}