{
    "product-insteadofprice": "31,90",
    "product-badge-image": "",
    "url": "https://www.spar.si/online/ponev-vok-28cm-tasty-11/p/598810",
    "title": "PONEV VOK 28CM, TASTY, 1/1",
    "product-promotionBadges": "",
    "isOnPromotion": "false",
    "product-price": "31,90",
    "product-info": {
        "contact-information": {
            "kontakt:": "FACKELMANN, D.O.O."
        },
        "product-net-cont": {
            "neto-količina": "1kos"
        }
    },
    "product-priceperunit": "31,90 €/Pieces",
    "teaser-text": "TASTY PONEV VOK 28CM",
    "product-badge-hostname": "https://www.spar.si",
    "product-stock-status": "",
    "product-amount": "",
    "description": "TASTY PONEV VOK 28CM",
    "teaser-image": "https://cdn1.interspar.at/cachableservlets/articleImage.dam/si/598810/dt_main.jpg",
    "product-brand": ""
}