{
    "product-amount": "",
    "product-badge-image": "",
    "teaser-text": "SI PONEV 28CM, 8948",
    "description": "SI PONEV 28CM, 8948",
    "product-info": {
        "product-net-cont": {
            "neto-količina": "1kos"
        },
        "opis": "S premazom proti prijemanju Teflon Classic. Primerna za uporabo na vseh kuhalnih površinah, razen indukcijskih. Primerna za pomivanje v pomivalnem stroju.",
        "contact-information": {
            "kontakt:": "SPAR Slovenija d.o.o., Letališka cesta 26, SI-1000 Ljubljana, Telefonska številka: 080 82 44"
        }
    },
    "title": "PONEV 28CM, SIMPEX",
    "url": "https://www.spar.si/online/ponev-28cm-simpex/p/391180",
    "isOnPromotion": "false",
    "product-priceperunit": "9,99 €/kos",
    "product-insteadofprice": "9,99",
    "product-stock-status": "",
    "product-price": "9,99",
    "product-brand": "",
    "product-promotionBadges": "",
    "product-badge-hostname": "https://www.spar.si",
    "teaser-image": "https://cdn1.interspar.at/cachableservlets/articleImage.dam/si/391180/dt_main.jpg"
}