{
    "product-insteadofprice": "2,35",
    "product-priceperunit": "33,57 €/kg",
    "product-badge-hostname": "https://www.spar.si",
    "product-badge-image": "",
    "title": "PRIBOLJŠEK ZA PSE, S SIROM, BEEF STICK QUADROS, VITAKRAFT, 70 G",
    "product-stock-status": "",
    "product-info": {
        "product-net-cont": {
            "neto-količina": "70g"
        },
        "contact-information": {
            "kontakt:": "Vitakraft Hobby program d.o.o., Klanjec 4, 10251 Hrv. Leskovac, Hrvaška"
        }
    },
    "description": "POSL.BEEF.ST.QUA.S.S.70G",
    "product-promotionBadges": "",
    "product-brand": "",
    "product-price": "2,35",
    "teaser-text": "POSL.BEEF.ST.QUA.S.S.70G",
    "isOnPromotion": "false",
    "url": "https://www.spar.si/online/priboljsek-za-pse-s-sirom-beef-stick-quadros-vitakraft-70-g/p/491332",
    "product-amount": "",
    "teaser-image": "https://cdn1.interspar.at/cachableservlets/articleImage.dam/si/491332/dt_main.jpg"
}