{
    "product-insteadofprice": "1,09",
    "product-badge-image": "/online/medias/sys_master/images/images/h68/h25/10524621799454/badge-cold-FIN.jpg",
    "url": "https://www.spar.si/online/rukola-veg-100g/p/559221",
    "title": "RUKOLA VEG, 100G",
    "product-promotionBadges": "",
    "isOnPromotion": "false",
    "product-price": "1,09",
    "product-info": {
        "product-net-cont": {
            "neto-količina": "100g"
        },
        "contact-information": {},
        "ingredient-information": {
            "temperatura-za-hranjenje": "hlajeno"
        }
    },
    "product-priceperunit": "10,90 €/kg",
    "teaser-text": "RUKOLA 100G",
    "product-badge-hostname": "https://www.spar.si",
    "product-stock-status": "",
    "product-amount": "",
    "description": "RUKOLA 100G",
    "teaser-image": "https://cdn1.interspar.at/cachableservlets/articleImage.dam/si/559221/dt_main.jpg",
    "product-brand": ""
}