{
    "product-insteadofprice": "2,29",
    "product-priceperunit": "0,23 €/kos",
    "product-badge-hostname": "https://www.spar.si",
    "product-badge-image": "",
    "title": "TOALETNI PAPIR 3 SLOJNI KAMILICA LOVELY, 10/1",
    "product-stock-status": "",
    "product-info": {
        "product-net-cont": {
            "neto-količina": "10kos"
        },
        "contact-information": {
            "kontakt:": "SPAR Slovenija d.o.o., Letališka cesta 26, 1000 Ljubljana, Tel.: 080 82 44"
        }
    },
    "description": "LOVELY TOAL.PAPIR 10/1",
    "product-promotionBadges": "",
    "product-brand": "",
    "product-price": "2,29",
    "teaser-text": "LOVELY TOAL.PAPIR 10/1",
    "isOnPromotion": "false",
    "url": "https://www.spar.si/online/toaletni-papir-3-slojni-kamilica-lovely-101/p/449592",
    "product-amount": "",
    "teaser-image": "https://cdn1.interspar.at/cachableservlets/articleImage.dam/si/449592/dt_main.jpg"
}