{
    "product-insteadofprice": "5,49",
    "product-badge-image": "",
    "url": "https://www.spar.si/online/tonic-water-orange-fentimans-4x02l/p/570699",
    "title": "TONIC WATER ORANGE, FENTIMANS, 4X0,2L",
    "product-promotionBadges": "",
    "isOnPromotion": "false",
    "product-price": "5,49",
    "product-info": {
        "contact-information": {
            "kontakt:": "MABAT INT. D.O.O., KAPELE 2, 8258 KAPELE"
        },
        "product-net-cont": {
            "neto-količina": "0,8l"
        }
    },
    "product-priceperunit": "6,86 €/l",
    "teaser-text": "TONIC FENTIM.ORANGE4X0,2",
    "product-badge-hostname": "https://www.spar.si",
    "product-stock-status": "",
    "product-amount": "",
    "description": "TONIC FENTIM.ORANGE4X0,2",
    "teaser-image": "https://cdn1.interspar.at/cachableservlets/articleImage.dam/si/570699/dt_main.jpg",
    "product-brand": ""
}