{
    "product-insteadofprice": "5,99",
    "product-badge-image": "/online/medias/sys_master/root/hf2/h7c/9039970435102/TZ-1.png",
    "url": "https://www.spar.si/online/vino-cabarnet-sauvignon-instinct-075l/p/579914",
    "title": "VINO CABARNET SAUVIGNON, INSTINCT, 0,75L",
    "product-promotionBadges": "",
    "isOnPromotion": "true",
    "product-price": "4,69",
    "product-info": {
        "product-net-cont": {
            "neto-količina": "0,75l"
        },
        "trade-group": {
            "vsebnost-alkohola": "14,50 vol. %"
        },
        "ingredient-information": {
            "alergeni": "ŽVEPLOV DIOKSID IN SULFITI."
        },
        "contact-information": {
            "kontakt:": "Puklavec Family Wines d.o.o."
        }
    },
    "product-priceperunit": "6,25 €/l",
    "teaser-text": "VINO CAB.SAUV.INST.0,75L",
    "product-badge-hostname": "https://www.spar.si",
    "product-stock-status": "",
    "product-amount": "",
    "description": "VINO CAB.SAUV.INST.0,75L",
    "teaser-image": "https://cdn1.interspar.at/cachableservlets/articleImage.dam/si/579914/dt_main.jpg",
    "product-brand": ""
}