{
    "product-insteadofprice": "1,45",
    "product-badge-image": "",
    "url": "https://www.spar.si/online/cebula-ocvrta-top-taste-150g/p/540864",
    "title": "ČEBULA OCVRTA, TOP TASTE, 150G",
    "product-promotionBadges": "",
    "isOnPromotion": "false",
    "product-price": "1,45",
    "product-info": {
        "contact-information": {
            "kontakt:": "Distributer: CJS, mednarodna trgovina d.o.o., Na klancu 11, 1295 Ivančna Gorica"
        },
        "product-net-cont": {
            "neto-količina": "150g"
        },
        "ingredient-information": {
            "alergeni": "GLUTEN."
        },
        "instruction-for-use": {
            "navodila-za-uporabo": "/"
        },
        "\n\t\t\t\tprehrambni-tip-artikla": "gotova jed",
        "base-information": {
            "neto-količina-plod:": "150G"
        }
    },
    "product-priceperunit": "9,67 €/kg",
    "teaser-text": "ČEBULA OCVR.TOPTASTE150G",
    "product-badge-hostname": "https://www.spar.si",
    "product-stock-status": "",
    "product-amount": "",
    "description": "ČEBULA OCVR.TOPTASTE150G",
    "teaser-image": "https://cdn1.interspar.at/cachableservlets/articleImage.dam/si/540864/dt_main.jpg",
    "product-brand": ""
}