{
    "product-info": {
        "security-warning": {
            "varnostna-opozorila": "Po vsakem čiščenju operite roke v čisti vodi. Hraniti izven dosega otrok."
        },
        "opis": "Večnamensko čistilo s čistilno močjo amoniaka. Raztopi in odstrani vse vrste umazanije, upočasni nabiranje prahu in za seboj pušča sijoče površine. Primeren je za čiščenje in lesk stekla, kuhinjskih pultov, ogledal, TV ekranov, avtomobilskih oken ter lakiranih, plastičnih, keramičnih in drugih pralnih površin.",
        "product-net-cont": {
            "neto-količina": "0,75l"
        },
        "contact-information": {
            "kontakt:": "Šampionka d.o.o., Šmarska cesta 5, 6000 Koper"
        },
        "ingredient-information": {
            "sestavine": "<5 % anionske površinsko aktivne snovi, dišave."
        },
        "instruction-for-use": {
            "navodila-za-uporabo": "Razpršilec namestite na plastenko in konico obrnite na položaj ON. Razpršite na površino in jo nato obrišite s čisto in suho krpo. Po uporabi konico na razpršilcu obrnite na položaj OFF."
        }
    },
    "product-brand": "",
    "url": "https://www.spar.si/online/cistilo-za-steklo-stelex-750ml-polnilo/p/116477",
    "product-price": "1,69",
    "teaser-image": "https://cdn1.interspar.at/cachableservlets/articleImage.dam/si/116477/dt_main.jpg",
    "product-badge-hostname": "https://www.spar.si",
    "product-badge-image": "",
    "product-insteadofprice": "1,69",
    "product-amount": "",
    "isOnPromotion": "false",
    "product-promotionBadges": "",
    "teaser-text": "ČISTILO STELEX 750ML",
    "product-stock-status": "",
    "title": "ČISTILO ZA STEKLO STELEX, 750ML, POLNILO",
    "product-priceperunit": "2,25 €/l",
    "description": "ČISTILO STELEX 750ML"
}