{
    "product-amount": "",
    "product-badge-image": "",
    "teaser-text": "LIKER ČOKOLADNI 0,7L",
    "description": "LIKER ČOKOLADNI 0,7L",
    "product-info": {
        "instruction-for-use": {
            "navodila-za-uporabo": "Čokoladni liker pijemo predvsem čistega. Serviramo ga lahko s kockami ledu in ga na ta način primerno hitro ohladimo. Primeren je tudi za pripravo koktajlov, ob kavi, za prelitje sladoleda in slaščic."
        },
        "product-net-cont": {
            "neto-količina": "0,7l"
        },
        "trade-group": {
            "vsebnost-alkohola": "18,00 vol. %"
        },
        "ingredient-information": {
            "alergeni": "JAJCA, SOJA, MLEKO, LEŠNIKI (V SLEDOVIH), MANDLJI (V SLEDOVIH)."
        },
        "contact-information": {
            "kontakt:": "FRUCTAL d.o.o., Tovarniška cesta 7, 5270 Ajdovščina"
        }
    },
    "title": "ČOKOLADNI LIKER MATISS, FRUCTAL, 0,7L",
    "url": "https://www.spar.si/online/cokoladni-liker-matiss-fructal-07l/p/41260",
    "isOnPromotion": "false",
    "product-priceperunit": "15,13 €/l",
    "product-insteadofprice": "10,59",
    "product-stock-status": "",
    "product-price": "10,59",
    "product-brand": "",
    "product-promotionBadges": "",
    "product-badge-hostname": "https://www.spar.si",
    "teaser-image": "https://cdn1.interspar.at/cachableservlets/articleImage.dam/si/41260/dt_main.jpg"
}