{
    "product-promotionBadges": "Izdelek v promociji",
    "product-insteadofprice": "3,27",
    "product-stock-status": "",
    "product-info": {
        "product-net-cont": {
            "neto-količina": "0,4l"
        },
        "contact-information": {}
    },
    "product-priceperunit": "8,18 €/l",
    "product-brand": "",
    "url": "https://www.spar.si/online/sampon-za-tanke-lase-q10-schauma-400ml/p/362623",
    "product-price": "3,27",
    "title": "ŠAMPON ZA TANKE LASE Q10, SCHAUMA, 400ML",
    "description": "ŠAMPON SCHAUMA Q10",
    "isOnPromotion": "true",
    "product-badge-hostname": "https://www.spar.si",
    "product-badge-image": "/online/medias/sys_master/root/h42/h77/9039969648670/akcija-1.png",
    "product-amount": "",
    "teaser-image": "https://cdn1.interspar.at/cachableservlets/articleImage.dam/si/362623/dt_main.jpg",
    "teaser-text": "ŠAMPON SCHAUMA Q10"
}