{
    "title": "ŠAMPON BREZA IN ARNIKA, AFRODITA, 1L",
    "product-badge-image": "",
    "teaser-image": "https://cdn1.interspar.at/cachableservlets/articleImage.dam/si/356345/dt_main.jpg",
    "product-badge-hostname": "https://www.spar.si",
    "product-insteadofprice": "2,99",
    "isOnPromotion": "false",
    "product-info": {
        "product-net-cont": {
            "neto-količina": "1l"
        },
        "contact-information": {
            "kontakt:": "Kozmetika Afrodita d.o.o., Kidričeva 54, 3250 Rogaška Slatina, Slovenija"
        },
        "opis": "Razmasti lase in lasišče, odpravlja prhljaj in krepi lasno strukturo. Za temeljito nego mastnih las in lasišča s prhljajem.- za mastne lase in lasišče s prhljajem",
        "ingredient-information": {}
    },
    "product-brand": "",
    "product-amount": "",
    "product-priceperunit": "2,99 €/l",
    "product-stock-status": "",
    "description": "ŠAMPON AFRODITA 1L",
    "product-price": "2,99",
    "product-promotionBadges": "",
    "teaser-text": "ŠAMPON AFRODITA 1L",
    "url": "https://www.spar.si/online/sampon-breza-in-arnika-afrodita-1l/p/356345"
}